MANIFEST.in
README
RELEASE-VERSION
setup.py
version.py
m4pomodoro/__init__.py
m4pomodoro/main.py
m4pomodoro.egg-info/PKG-INFO
m4pomodoro.egg-info/SOURCES.txt
m4pomodoro.egg-info/dependency_links.txt
m4pomodoro.egg-info/entry_points.txt
m4pomodoro.egg-info/requires.txt
m4pomodoro.egg-info/top_level.txt
m4pomodoro/data/tomate_blue.svg
m4pomodoro/data/tomate_green.svg
m4pomodoro/data/tomate_red.svg
m4pomodoro/data/tomate_yellow.svg