Metadata-Version: 1.0
Name: m4pomodoro
Version: 0.1.1.post3.dev101723961
Summary: simple pomodoro app
Home-page: UNKNOWN
Author: Marc Siegenthaler
Author-email: shin@marcsi.ch
License: MIT
Keywords: tray pomodoro
Platform: UNKNOWN
